ynab_bulk_rename.py
ynab_bulk_rename-0.1.0.dist-info/METADATA
ynab_bulk_rename-0.1.0.dist-info/WHEEL
ynab_bulk_rename-0.1.0.dist-info/entry_points.txt
ynab_bulk_rename-0.1.0.dist-info/licenses/LICENSE
ynab_bulk_rename-0.1.0.dist-info/RECORD
