Metadata-Version: 2.4
Name: ynab-bulk-rename
Version: 0.1.0
Summary: A CLI tool to bulk rename YNAB payees that match a specific pattern
Project-URL: Homepage, https://github.com/codingcastor/ynab-bulk-rename
Project-URL: Repository, https://github.com/codingcastor/ynab-bulk-rename
Project-URL: Issues, https://github.com/codingcastor/ynab-bulk-rename/issues
Project-URL: Documentation, https://github.com/codingcastor/ynab-bulk-rename#readme
Author-email: "Raphaël H." <contact@codingcastor.com>
Maintainer-email: "Raphaël H." <contact@codingcastor.com>
License: MIT
License-File: LICENSE
Keywords: budgeting,bulk,cli,payee,rename,ynab
Classifier: Development Status :: 4 - Beta
Classifier: Environment :: Console
Classifier: Intended Audience :: End Users/Desktop
Classifier: License :: OSI Approved :: MIT License
Classifier: Operating System :: OS Independent
Classifier: Programming Language :: Python :: 3
Classifier: Programming Language :: Python :: 3.10
Classifier: Programming Language :: Python :: 3.11
Classifier: Programming Language :: Python :: 3.12
Classifier: Topic :: Office/Business :: Financial
Classifier: Topic :: Utilities
Requires-Python: >=3.10
Requires-Dist: requests<3.0.0,>=2.31.0
